{
    "comuna": "Iquique",
    "estaciones": [
        {
            "id": 29,
            "marca": 5,
            "direccion": "VIVAR 402",
            "latitud": "-20.213349467685262",
            "longitud": "-70.14856606721878",
            "region": "Tarapacá",
            "comuna": "Iquique",
            "en_mantenimiento_bandera": 0,
            "electrolinera_bandera": 0,
            "gasolinera_bandera": 1,
            "imagen": "/storage/logo/1697478048_logo5.jpg",
            "logo": "https://api.bencinaenlinea.cl/storage/logo/1697478048_logo5.jpg",
            "likes": 0,
            "dislikes": 0,
            "usuario_favorito": null,
            "usuario_likes": null,
            "horario": null,
            "combustibles": [
                {
                    "id": 1,
                    "nombre_corto": "93",
                    "nombre_largo": "Gasolina 93",
                    "suministra": 1,
                    "estacion_id": 29,
                    "precio": "1249.000",
                    "unidad_cobro": "$/L",
                    "actualizado": "hace 6 días",
                    "precio_fecha": "2026-03-19 13:34:46",
                    "updated_at": "2026-03-19 13:34:46",
                    "clase": "Gasolina",
                    "tipo_atencion": 2,
                    "tipo_atencion_nombre": "AutoServicio",
                    "orden": 12
                },
                {
                    "id": 2,
                    "nombre_corto": "97",
                    "nombre_largo": "Gasolina 97",
                    "suministra": 1,
                    "estacion_id": 29,
                    "precio": "1288.000",
                    "unidad_cobro": "$/L",
                    "actualizado": "hace 6 días",
                    "precio_fecha": "2026-03-19 13:35:10",
                    "updated_at": "2026-03-19 13:35:10",
                    "clase": "Gasolina",
                    "tipo_atencion": 2,
                    "tipo_atencion_nombre": "AutoServicio",
                    "orden": 10
                },
                {
                    "id": 3,
                    "nombre_corto": "DI",
                    "nombre_largo": "Petroleo Diesel",
                    "suministra": 1,
                    "estacion_id": 29,
                    "precio": "994.000",
                    "unidad_cobro": "$/L",
                    "actualizado": "hace 1 semana",
                    "precio_fecha": "2026-03-16 15:29:19",
                    "updated_at": "2026-03-16 15:29:19",
                    "clase": "Gas",
                    "tipo_atencion": 2,
                    "tipo_atencion_nombre": "AutoServicio",
                    "orden": 9
                },
                {
                    "id": 7,
                    "nombre_corto": "95",
                    "nombre_largo": "Gasolina 95",
                    "suministra": 1,
                    "estacion_id": 29,
                    "precio": "1268.000",
                    "unidad_cobro": "$/L",
                    "actualizado": "hace 6 días",
                    "precio_fecha": "2026-03-19 13:34:46",
                    "updated_at": "2026-03-19 13:34:46",
                    "clase": "Gasolina",
                    "tipo_atencion": 2,
                    "tipo_atencion_nombre": "AutoServicio",
                    "orden": 11
                }
            ],
            "atenciones": [],
            "servicios": [
                {
                    "id": null,
                    "nombre": null,
                    "estacion_id": 29
                }
            ],
            "control_calidad": [],
            "nombre_bencinera": "COPEC"
        },
        {
            "id": 30,
            "marca": 5,
            "direccion": "SITIO 54B BARRIO INDUSTRIAL",
            "latitud": "-20.20475046538578",
            "longitud": "-70.14159232378006",
            "region": "Tarapacá",
            "comuna": "Iquique",
            "en_mantenimiento_bandera": 0,
            "electrolinera_bandera": 0,
            "gasolinera_bandera": 1,
            "imagen": "/storage/logo/1697478048_logo5.jpg",
            "logo": "https://api.bencinaenlinea.cl/storage/logo/1697478048_logo5.jpg",
            "likes": 0,
            "dislikes": 0,
            "usuario_favorito": null,
            "usuario_likes": null,
            "horario": null,
            "combustibles": [
                {
                    "id": 1,
                    "nombre_corto": "93",
                    "nombre_largo": "Gasolina 93",
                    "suministra": 1,
                    "estacion_id": 30,
                    "precio": "1245.000",
                    "unidad_cobro": "$/L",
                    "actualizado": "hace 5 días",
                    "precio_fecha": "2026-03-20 13:39:20",
                    "updated_at": "2026-03-20 13:39:20",
                    "clase": "Gasolina",
                    "tipo_atencion": 2,
                    "tipo_atencion_nombre": "AutoServicio",
                    "orden": 12
                },
                {
                    "id": 2,
                    "nombre_corto": "97",
                    "nombre_largo": "Gasolina 97",
                    "suministra": 1,
                    "estacion_id": 30,
                    "precio": "1289.000",
                    "unidad_cobro": "$/L",
                    "actualizado": "hace 5 días",
                    "precio_fecha": "2026-03-20 13:39:20",
                    "updated_at": "2026-03-20 13:39:20",
                    "clase": "Gasolina",
                    "tipo_atencion": 2,
                    "tipo_atencion_nombre": "AutoServicio",
                    "orden": 10
                },
                {
                    "id": 3,
                    "nombre_corto": "DI",
                    "nombre_largo": "Petroleo Diesel",
                    "suministra": 1,
                    "estacion_id": 30,
                    "precio": "990.000",
                    "unidad_cobro": "$/L",
                    "actualizado": "hace 5 días",
                    "precio_fecha": "2026-03-20 13:39:20",
                    "updated_at": "2026-03-20 13:39:20",
                    "clase": "Gas",
                    "tipo_atencion": 2,
                    "tipo_atencion_nombre": "AutoServicio",
                    "orden": 9
                },
                {
                    "id": 7,
                    "nombre_corto": "95",
                    "nombre_largo": "Gasolina 95",
                    "suministra": 1,
                    "estacion_id": 30,
                    "precio": "1264.000",
                    "unidad_cobro": "$/L",
                    "actualizado": "hace 5 días",
                    "precio_fecha": "2026-03-20 13:39:20",
                    "updated_at": "2026-03-20 13:39:20",
                    "clase": "Gasolina",
                    "tipo_atencion": 2,
                    "tipo_atencion_nombre": "AutoServicio",
                    "orden": 11
                }
            ],
            "atenciones": [],
            "servicios": [
                {
                    "id": null,
                    "nombre": null,
                    "estacion_id": 30
                }
            ],
            "control_calidad": [],
            "nombre_bencinera": "COPEC"
        },
        {
            "id": 31,
            "marca": 5,
            "direccion": " Avda. Salvador Allende 2345",
            "latitud": "-20.2564238",
            "longitud": "-70.12807659999999",
            "region": "Tarapacá",
            "comuna": "Iquique",
            "en_mantenimiento_bandera": 0,
            "electrolinera_bandera": 0,
            "gasolinera_bandera": 1,
            "imagen": "/storage/logo/1697478048_logo5.jpg",
            "logo": "https://api.bencinaenlinea.cl/storage/logo/1697478048_logo5.jpg",
            "likes": 0,
            "dislikes": 0,
            "usuario_favorito": null,
            "usuario_likes": null,
            "horario": null,
            "combustibles": [
                {
                    "id": 3,
                    "nombre_corto": "DI",
                    "nombre_largo": "Petroleo Diesel",
                    "suministra": 1,
                    "estacion_id": 31,
                    "precio": "982.000",
                    "unidad_cobro": "$/L",
                    "actualizado": "hace 1 semana",
                    "precio_fecha": "2026-03-16 11:10:19",
                    "updated_at": "2026-03-16 11:10:19",
                    "clase": "Gas",
                    "tipo_atencion": 2,
                    "tipo_atencion_nombre": "AutoServicio",
                    "orden": 9
                },
                {
                    "id": 8,
                    "nombre_corto": "A93",
                    "nombre_largo": "Gasolina 93",
                    "suministra": 1,
                    "estacion_id": 31,
                    "precio": "1241.000",
                    "unidad_cobro": "$/L",
                    "actualizado": "hace 6 días",
                    "precio_fecha": "2026-03-19 07:49:22",
                    "updated_at": "2026-03-19 07:49:22",
                    "clase": "Gas",
                    "tipo_atencion": 1,
                    "tipo_atencion_nombre": "Asistido",
                    "orden": 5
                },
                {
                    "id": 9,
                    "nombre_corto": "A95",
                    "nombre_largo": "Gasolina 95",
                    "suministra": 1,
                    "estacion_id": 31,
                    "precio": "1260.000",
                    "unidad_cobro": "$/L",
                    "actualizado": "hace 6 días",
                    "precio_fecha": "2026-03-19 07:49:22",
                    "updated_at": "2026-03-19 07:49:22",
                    "clase": "Gas",
                    "tipo_atencion": 1,
                    "tipo_atencion_nombre": "Asistido",
                    "orden": 4
                },
                {
                    "id": 10,
                    "nombre_corto": "A97",
                    "nombre_largo": "Gasolina 97",
                    "suministra": 1,
                    "estacion_id": 31,
                    "precio": "1285.000",
                    "unidad_cobro": "$/L",
                    "actualizado": "hace 6 días",
                    "precio_fecha": "2026-03-19 07:49:22",
                    "updated_at": "2026-03-19 07:49:22",
                    "clase": "Gas",
                    "tipo_atencion": 1,
                    "tipo_atencion_nombre": "Asistido",
                    "orden": 3
                },
                {
                    "id": 11,
                    "nombre_corto": "ADI",
                    "nombre_largo": "Petroleo Diesel",
                    "suministra": 1,
                    "estacion_id": 31,
                    "precio": "974.000",
                    "unidad_cobro": "$/L",
                    "actualizado": "hace 1 semana",
                    "precio_fecha": "2026-03-16 11:10:19",
                    "updated_at": "2026-03-16 11:10:19",
                    "clase": "Gas",
                    "tipo_atencion": 1,
                    "tipo_atencion_nombre": "Asistido",
                    "orden": 2
                }
            ],
            "atenciones": [],
            "servicios": [],
            "control_calidad": [],
            "nombre_bencinera": "COPEC"
        },
        {
            "id": 32,
            "marca": 5,
            "direccion": "Salvador Allende 2102",
            "latitud": "-20.228987",
            "longitud": "-70.13542359999997",
            "region": "Tarapacá",
            "comuna": "Iquique",
            "en_mantenimiento_bandera": 0,
            "electrolinera_bandera": 0,
            "gasolinera_bandera": 1,
            "imagen": "/storage/logo/1697478048_logo5.jpg",
            "logo": "https://api.bencinaenlinea.cl/storage/logo/1697478048_logo5.jpg",
            "likes": 0,
            "dislikes": 0,
            "usuario_favorito": null,
            "usuario_likes": null,
            "horario": null,
            "combustibles": [
                {
                    "id": 1,
                    "nombre_corto": "93",
                    "nombre_largo": "Gasolina 93",
                    "suministra": 1,
                    "estacion_id": 32,
                    "precio": "1246.000",
                    "unidad_cobro": "$/L",
                    "actualizado": "hace 6 días",
                    "precio_fecha": "2026-03-18 23:09:08",
                    "updated_at": "2026-03-18 23:09:08",
                    "clase": "Gasolina",
                    "tipo_atencion": 2,
                    "tipo_atencion_nombre": "AutoServicio",
                    "orden": 12
                },
                {
                    "id": 2,
                    "nombre_corto": "97",
                    "nombre_largo": "Gasolina 97",
                    "suministra": 1,
                    "estacion_id": 32,
                    "precio": "1290.000",
                    "unidad_cobro": "$/L",
                    "actualizado": "hace 6 días",
                    "precio_fecha": "2026-03-18 23:09:08",
                    "updated_at": "2026-03-18 23:09:08",
                    "clase": "Gasolina",
                    "tipo_atencion": 2,
                    "tipo_atencion_nombre": "AutoServicio",
                    "orden": 10
                },
                {
                    "id": 3,
                    "nombre_corto": "DI",
                    "nombre_largo": "Petroleo Diesel",
                    "suministra": 1,
                    "estacion_id": 32,
                    "precio": "994.000",
                    "unidad_cobro": "$/L",
                    "actualizado": "hace 6 días",
                    "precio_fecha": "2026-03-18 23:09:08",
                    "updated_at": "2026-03-18 23:09:08",
                    "clase": "Gas",
                    "tipo_atencion": 2,
                    "tipo_atencion_nombre": "AutoServicio",
                    "orden": 9
                },
                {
                    "id": 7,
                    "nombre_corto": "95",
                    "nombre_largo": "Gasolina 95",
                    "suministra": 1,
                    "estacion_id": 32,
                    "precio": "1265.000",
                    "unidad_cobro": "$/L",
                    "actualizado": "hace 6 días",
                    "precio_fecha": "2026-03-18 23:09:08",
                    "updated_at": "2026-03-18 23:09:08",
                    "clase": "Gasolina",
                    "tipo_atencion": 2,
                    "tipo_atencion_nombre": "AutoServicio",
                    "orden": 11
                }
            ],
            "atenciones": [],
            "servicios": [],
            "control_calidad": [],
            "nombre_bencinera": "COPEC"
        },
        {
            "id": 33,
            "marca": 5,
            "direccion": "MANUEL RODRIGUEZ 1404",
            "latitud": "-20.223392047740003",
            "longitud": "-70.14222264289856",
            "region": "Tarapacá",
            "comuna": "Iquique",
            "en_mantenimiento_bandera": 0,
            "electrolinera_bandera": 0,
            "gasolinera_bandera": 1,
            "imagen": "/storage/logo/1697478048_logo5.jpg",
            "logo": "https://api.bencinaenlinea.cl/storage/logo/1697478048_logo5.jpg",
            "likes": 0,
            "dislikes": 0,
            "usuario_favorito": null,
            "usuario_likes": null,
            "horario": null,
            "combustibles": [
                {
                    "id": 1,
                    "nombre_corto": "93",
                    "nombre_largo": "Gasolina 93",
                    "suministra": 1,
                    "estacion_id": 33,
                    "precio": "1241.000",
                    "unidad_cobro": "$/L",
                    "actualizado": "hace 6 días",
                    "precio_fecha": "2026-03-18 23:07:02",
                    "updated_at": "2026-03-18 23:07:02",
                    "clase": "Gasolina",
                    "tipo_atencion": 2,
                    "tipo_atencion_nombre": "AutoServicio",
                    "orden": 12
                },
                {
                    "id": 2,
                    "nombre_corto": "97",
                    "nombre_largo": "Gasolina 97",
                    "suministra": 1,
                    "estacion_id": 33,
                    "precio": "1281.000",
                    "unidad_cobro": "$/L",
                    "actualizado": "hace 6 días",
                    "precio_fecha": "2026-03-18 23:07:02",
                    "updated_at": "2026-03-18 23:07:02",
                    "clase": "Gasolina",
                    "tipo_atencion": 2,
                    "tipo_atencion_nombre": "AutoServicio",
                    "orden": 10
                },
                {
                    "id": 3,
                    "nombre_corto": "DI",
                    "nombre_largo": "Petroleo Diesel",
                    "suministra": 1,
                    "estacion_id": 33,
                    "precio": "986.000",
                    "unidad_cobro": "$/L",
                    "actualizado": "hace 6 días",
                    "precio_fecha": "2026-03-18 23:07:02",
                    "updated_at": "2026-03-18 23:07:02",
                    "clase": "Gas",
                    "tipo_atencion": 2,
                    "tipo_atencion_nombre": "AutoServicio",
                    "orden": 9
                },
                {
                    "id": 7,
                    "nombre_corto": "95",
                    "nombre_largo": "Gasolina 95",
                    "suministra": 1,
                    "estacion_id": 33,
                    "precio": "1260.000",
                    "unidad_cobro": "$/L",
                    "actualizado": "hace 6 días",
                    "precio_fecha": "2026-03-18 23:07:02",
                    "updated_at": "2026-03-18 23:07:02",
                    "clase": "Gasolina",
                    "tipo_atencion": 2,
                    "tipo_atencion_nombre": "AutoServicio",
                    "orden": 11
                }
            ],
            "atenciones": [],
            "servicios": [],
            "control_calidad": [],
            "nombre_bencinera": "COPEC"
        },
        {
            "id": 34,
            "marca": 5,
            "direccion": "ANIBAL PINTO 1377",
            "latitud": "-20.22102618499956",
            "longitud": "-70.15311777591705",
            "region": "Tarapacá",
            "comuna": "Iquique",
            "en_mantenimiento_bandera": 0,
            "electrolinera_bandera": 0,
            "gasolinera_bandera": 1,
            "imagen": "/storage/logo/1697478048_logo5.jpg",
            "logo": "https://api.bencinaenlinea.cl/storage/logo/1697478048_logo5.jpg",
            "likes": 0,
            "dislikes": 0,
            "usuario_favorito": null,
            "usuario_likes": null,
            "horario": null,
            "combustibles": [
                {
                    "id": 1,
                    "nombre_corto": "93",
                    "nombre_largo": "Gasolina 93",
                    "suministra": 1,
                    "estacion_id": 34,
                    "precio": "1245.000",
                    "unidad_cobro": "$/L",
                    "actualizado": "hace 5 días",
                    "precio_fecha": "2026-03-20 12:26:11",
                    "updated_at": "2026-03-20 12:26:11",
                    "clase": "Gasolina",
                    "tipo_atencion": 2,
                    "tipo_atencion_nombre": "AutoServicio",
                    "orden": 12
                },
                {
                    "id": 2,
                    "nombre_corto": "97",
                    "nombre_largo": "Gasolina 97",
                    "suministra": 1,
                    "estacion_id": 34,
                    "precio": "1289.000",
                    "unidad_cobro": "$/L",
                    "actualizado": "hace 5 días",
                    "precio_fecha": "2026-03-20 12:26:11",
                    "updated_at": "2026-03-20 12:26:11",
                    "clase": "Gasolina",
                    "tipo_atencion": 2,
                    "tipo_atencion_nombre": "AutoServicio",
                    "orden": 10
                },
                {
                    "id": 3,
                    "nombre_corto": "DI",
                    "nombre_largo": "Petroleo Diesel",
                    "suministra": 1,
                    "estacion_id": 34,
                    "precio": "990.000",
                    "unidad_cobro": "$/L",
                    "actualizado": "hace 5 días",
                    "precio_fecha": "2026-03-20 12:26:11",
                    "updated_at": "2026-03-20 12:26:11",
                    "clase": "Gas",
                    "tipo_atencion": 2,
                    "tipo_atencion_nombre": "AutoServicio",
                    "orden": 9
                },
                {
                    "id": 7,
                    "nombre_corto": "95",
                    "nombre_largo": "Gasolina 95",
                    "suministra": 1,
                    "estacion_id": 34,
                    "precio": "1264.000",
                    "unidad_cobro": "$/L",
                    "actualizado": "hace 5 días",
                    "precio_fecha": "2026-03-20 12:26:11",
                    "updated_at": "2026-03-20 12:26:11",
                    "clase": "Gasolina",
                    "tipo_atencion": 2,
                    "tipo_atencion_nombre": "AutoServicio",
                    "orden": 11
                }
            ],
            "atenciones": [],
            "servicios": [],
            "control_calidad": [],
            "nombre_bencinera": "COPEC"
        },
        {
            "id": 35,
            "marca": 5,
            "direccion": "Avda. Arturo Prat Chacon 1732",
            "latitud": "-20.241371428222784",
            "longitud": "-70.14390707015991",
            "region": "Tarapacá",
            "comuna": "Iquique",
            "en_mantenimiento_bandera": 0,
            "electrolinera_bandera": 0,
            "gasolinera_bandera": 1,
            "imagen": "/storage/logo/1697478048_logo5.jpg",
            "logo": "https://api.bencinaenlinea.cl/storage/logo/1697478048_logo5.jpg",
            "likes": 0,
            "dislikes": 0,
            "usuario_favorito": null,
            "usuario_likes": null,
            "horario": null,
            "combustibles": [
                {
                    "id": 1,
                    "nombre_corto": "93",
                    "nombre_largo": "Gasolina 93",
                    "suministra": 1,
                    "estacion_id": 35,
                    "precio": "1245.000",
                    "unidad_cobro": "$/L",
                    "actualizado": "hace 4 días",
                    "precio_fecha": "2026-03-21 06:42:59",
                    "updated_at": "2026-03-21 06:42:59",
                    "clase": "Gasolina",
                    "tipo_atencion": 2,
                    "tipo_atencion_nombre": "AutoServicio",
                    "orden": 12
                },
                {
                    "id": 2,
                    "nombre_corto": "97",
                    "nombre_largo": "Gasolina 97",
                    "suministra": 1,
                    "estacion_id": 35,
                    "precio": "1286.000",
                    "unidad_cobro": "$/L",
                    "actualizado": "hace 6 días",
                    "precio_fecha": "2026-03-19 06:57:28",
                    "updated_at": "2026-03-19 06:57:28",
                    "clase": "Gasolina",
                    "tipo_atencion": 2,
                    "tipo_atencion_nombre": "AutoServicio",
                    "orden": 10
                },
                {
                    "id": 3,
                    "nombre_corto": "DI",
                    "nombre_largo": "Petroleo Diesel",
                    "suministra": 1,
                    "estacion_id": 35,
                    "precio": "990.000",
                    "unidad_cobro": "$/L",
                    "actualizado": "hace 4 días",
                    "precio_fecha": "2026-03-21 06:42:59",
                    "updated_at": "2026-03-21 06:42:59",
                    "clase": "Gas",
                    "tipo_atencion": 2,
                    "tipo_atencion_nombre": "AutoServicio",
                    "orden": 9
                },
                {
                    "id": 7,
                    "nombre_corto": "95",
                    "nombre_largo": "Gasolina 95",
                    "suministra": 1,
                    "estacion_id": 35,
                    "precio": "1264.000",
                    "unidad_cobro": "$/L",
                    "actualizado": "hace 4 días",
                    "precio_fecha": "2026-03-21 06:42:59",
                    "updated_at": "2026-03-21 06:42:59",
                    "clase": "Gasolina",
                    "tipo_atencion": 2,
                    "tipo_atencion_nombre": "AutoServicio",
                    "orden": 11
                },
                {
                    "id": 8,
                    "nombre_corto": "A93",
                    "nombre_largo": "Gasolina 93",
                    "suministra": 1,
                    "estacion_id": 35,
                    "precio": "1230.000",
                    "unidad_cobro": "$/L",
                    "actualizado": "hace 4 días",
                    "precio_fecha": "2026-03-21 06:42:59",
                    "updated_at": "2026-03-21 06:42:59",
                    "clase": "Gas",
                    "tipo_atencion": 1,
                    "tipo_atencion_nombre": "Asistido",
                    "orden": 5
                },
                {
                    "id": 9,
                    "nombre_corto": "A95",
                    "nombre_largo": "Gasolina 95",
                    "suministra": 1,
                    "estacion_id": 35,
                    "precio": "1258.000",
                    "unidad_cobro": "$/L",
                    "actualizado": "hace 4 días",
                    "precio_fecha": "2026-03-21 06:42:59",
                    "updated_at": "2026-03-21 06:42:59",
                    "clase": "Gas",
                    "tipo_atencion": 1,
                    "tipo_atencion_nombre": "Asistido",
                    "orden": 4
                },
                {
                    "id": 10,
                    "nombre_corto": "A97",
                    "nombre_largo": "Gasolina 97",
                    "suministra": 1,
                    "estacion_id": 35,
                    "precio": "1271.000",
                    "unidad_cobro": "$/L",
                    "actualizado": "hace 6 días",
                    "precio_fecha": "2026-03-19 06:57:28",
                    "updated_at": "2026-03-19 06:57:28",
                    "clase": "Gas",
                    "tipo_atencion": 1,
                    "tipo_atencion_nombre": "Asistido",
                    "orden": 3
                },
                {
                    "id": 11,
                    "nombre_corto": "ADI",
                    "nombre_largo": "Petroleo Diesel",
                    "suministra": 1,
                    "estacion_id": 35,
                    "precio": "975.000",
                    "unidad_cobro": "$/L",
                    "actualizado": "hace 4 días",
                    "precio_fecha": "2026-03-21 06:42:59",
                    "updated_at": "2026-03-21 06:42:59",
                    "clase": "Gas",
                    "tipo_atencion": 1,
                    "tipo_atencion_nombre": "Asistido",
                    "orden": 2
                }
            ],
            "atenciones": [],
            "servicios": [
                {
                    "id": null,
                    "nombre": null,
                    "estacion_id": 35
                },
                {
                    "id": null,
                    "nombre": null,
                    "estacion_id": 35
                },
                {
                    "id": null,
                    "nombre": null,
                    "estacion_id": 35
                },
                {
                    "id": null,
                    "nombre": null,
                    "estacion_id": 35
                },
                {
                    "id": null,
                    "nombre": null,
                    "estacion_id": 35
                },
                {
                    "id": null,
                    "nombre": null,
                    "estacion_id": 35
                },
                {
                    "id": null,
                    "nombre": null,
                    "estacion_id": 35
                }
            ],
            "control_calidad": [],
            "nombre_bencinera": "COPEC"
        },
        {
            "id": 36,
            "marca": 24,
            "direccion": "AVDA.CIRCUNVALACION 720",
            "latitud": "-20.213696815862907",
            "longitud": "-70.13160109519958",
            "region": "Tarapacá",
            "comuna": "Iquique",
            "en_mantenimiento_bandera": 0,
            "electrolinera_bandera": 0,
            "gasolinera_bandera": 1,
            "imagen": "/storage/logo/1697478349_logo24.jpg",
            "logo": "https://api.bencinaenlinea.cl/storage/logo/1697478349_logo24.jpg",
            "likes": 0,
            "dislikes": 0,
            "usuario_favorito": null,
            "usuario_likes": null,
            "horario": null,
            "combustibles": [
                {
                    "id": 6,
                    "nombre_corto": "GLP",
                    "nombre_largo": "GLP Vehicular",
                    "suministra": 1,
                    "estacion_id": 36,
                    "precio": "836.000",
                    "unidad_cobro": "$/m3",
                    "actualizado": "hace 1 año",
                    "precio_fecha": "2024-08-01 08:28:29",
                    "updated_at": "2024-08-01 08:28:29",
                    "clase": "Gas",
                    "tipo_atencion": 2,
                    "tipo_atencion_nombre": "AutoServicio",
                    "orden": 6
                }
            ],
            "atenciones": [],
            "servicios": [],
            "control_calidad": [],
            "nombre_bencinera": "LIPIGAS"
        },
        {
            "id": 40,
            "marca": 151,
            "direccion": "Av. Arturo Prat 3415",
            "latitud": "-20.25879011472052",
            "longitud": "-70.13311922550201",
            "region": "Tarapacá",
            "comuna": "Iquique",
            "en_mantenimiento_bandera": 0,
            "electrolinera_bandera": 0,
            "gasolinera_bandera": 1,
            "imagen": "/storage/logo/1715355420_Aramco1.jpg",
            "logo": "https://api.bencinaenlinea.cl/storage/logo/1715355420_Aramco1.jpg",
            "likes": 0,
            "dislikes": 0,
            "usuario_favorito": null,
            "usuario_likes": null,
            "horario": null,
            "combustibles": [
                {
                    "id": 1,
                    "nombre_corto": "93",
                    "nombre_largo": "Gasolina 93",
                    "suministra": 1,
                    "estacion_id": 40,
                    "precio": "1249.000",
                    "unidad_cobro": "$/L",
                    "actualizado": "hace 6 días",
                    "precio_fecha": "2026-03-19 09:58:15",
                    "updated_at": "2026-03-19 09:58:15",
                    "clase": "Gasolina",
                    "tipo_atencion": 2,
                    "tipo_atencion_nombre": "AutoServicio",
                    "orden": 12
                },
                {
                    "id": 2,
                    "nombre_corto": "97",
                    "nombre_largo": "Gasolina 97",
                    "suministra": 1,
                    "estacion_id": 40,
                    "precio": "1286.000",
                    "unidad_cobro": "$/L",
                    "actualizado": "hace 6 días",
                    "precio_fecha": "2026-03-19 09:58:15",
                    "updated_at": "2026-03-19 09:58:15",
                    "clase": "Gasolina",
                    "tipo_atencion": 2,
                    "tipo_atencion_nombre": "AutoServicio",
                    "orden": 10
                },
                {
                    "id": 3,
                    "nombre_corto": "DI",
                    "nombre_largo": "Petroleo Diesel",
                    "suministra": 1,
                    "estacion_id": 40,
                    "precio": "994.000",
                    "unidad_cobro": "$/L",
                    "actualizado": "hace 6 días",
                    "precio_fecha": "2026-03-19 09:58:15",
                    "updated_at": "2026-03-19 09:58:15",
                    "clase": "Gas",
                    "tipo_atencion": 2,
                    "tipo_atencion_nombre": "AutoServicio",
                    "orden": 9
                },
                {
                    "id": 7,
                    "nombre_corto": "95",
                    "nombre_largo": "Gasolina 95",
                    "suministra": 1,
                    "estacion_id": 40,
                    "precio": "1268.000",
                    "unidad_cobro": "$/L",
                    "actualizado": "hace 6 días",
                    "precio_fecha": "2026-03-19 09:58:15",
                    "updated_at": "2026-03-19 09:58:15",
                    "clase": "Gasolina",
                    "tipo_atencion": 2,
                    "tipo_atencion_nombre": "AutoServicio",
                    "orden": 11
                }
            ],
            "atenciones": [],
            "servicios": [
                {
                    "id": null,
                    "nombre": null,
                    "estacion_id": 40
                },
                {
                    "id": null,
                    "nombre": null,
                    "estacion_id": 40
                }
            ],
            "control_calidad": [],
            "nombre_bencinera": "ARAMCO"
        },
        {
            "id": 41,
            "marca": 151,
            "direccion": "Av. Arturo Prat 1656",
            "latitud": "-20.23997221176155",
            "longitud": "-70.14508724212646",
            "region": "Tarapacá",
            "comuna": "Iquique",
            "en_mantenimiento_bandera": 0,
            "electrolinera_bandera": 0,
            "gasolinera_bandera": 1,
            "imagen": "/storage/logo/1715355420_Aramco1.jpg",
            "logo": "https://api.bencinaenlinea.cl/storage/logo/1715355420_Aramco1.jpg",
            "likes": 0,
            "dislikes": 0,
            "usuario_favorito": null,
            "usuario_likes": null,
            "horario": null,
            "combustibles": [
                {
                    "id": 1,
                    "nombre_corto": "93",
                    "nombre_largo": "Gasolina 93",
                    "suministra": 1,
                    "estacion_id": 41,
                    "precio": "1254.000",
                    "unidad_cobro": "$/L",
                    "actualizado": "hace 2 semanas",
                    "precio_fecha": "2026-03-05 19:30:40",
                    "updated_at": "2026-03-05 19:30:40",
                    "clase": "Gasolina",
                    "tipo_atencion": 2,
                    "tipo_atencion_nombre": "AutoServicio",
                    "orden": 12
                },
                {
                    "id": 2,
                    "nombre_corto": "97",
                    "nombre_largo": "Gasolina 97",
                    "suministra": 1,
                    "estacion_id": 41,
                    "precio": "1289.000",
                    "unidad_cobro": "$/L",
                    "actualizado": "hace 2 semanas",
                    "precio_fecha": "2026-03-05 19:30:40",
                    "updated_at": "2026-03-05 19:30:40",
                    "clase": "Gasolina",
                    "tipo_atencion": 2,
                    "tipo_atencion_nombre": "AutoServicio",
                    "orden": 10
                },
                {
                    "id": 3,
                    "nombre_corto": "DI",
                    "nombre_largo": "Petroleo Diesel",
                    "suministra": 1,
                    "estacion_id": 41,
                    "precio": "995.000",
                    "unidad_cobro": "$/L",
                    "actualizado": "hace 2 semanas",
                    "precio_fecha": "2026-03-05 14:32:04",
                    "updated_at": "2026-03-05 14:32:04",
                    "clase": "Gas",
                    "tipo_atencion": 2,
                    "tipo_atencion_nombre": "AutoServicio",
                    "orden": 9
                },
                {
                    "id": 7,
                    "nombre_corto": "95",
                    "nombre_largo": "Gasolina 95",
                    "suministra": 1,
                    "estacion_id": 41,
                    "precio": "1273.000",
                    "unidad_cobro": "$/L",
                    "actualizado": "hace 2 semanas",
                    "precio_fecha": "2026-03-05 19:30:40",
                    "updated_at": "2026-03-05 19:30:40",
                    "clase": "Gasolina",
                    "tipo_atencion": 2,
                    "tipo_atencion_nombre": "AutoServicio",
                    "orden": 11
                }
            ],
            "atenciones": [],
            "servicios": [],
            "control_calidad": [],
            "nombre_bencinera": "ARAMCO"
        },
        {
            "id": 42,
            "marca": 151,
            "direccion": "Av. Tadeo Haenke 1808",
            "latitud": "-20.23799919447965",
            "longitud": "-70.14375686645508",
            "region": "Tarapacá",
            "comuna": "Iquique",
            "en_mantenimiento_bandera": 0,
            "electrolinera_bandera": 0,
            "gasolinera_bandera": 1,
            "imagen": "/storage/logo/1715355420_Aramco1.jpg",
            "logo": "https://api.bencinaenlinea.cl/storage/logo/1715355420_Aramco1.jpg",
            "likes": 0,
            "dislikes": 0,
            "usuario_favorito": null,
            "usuario_likes": null,
            "horario": null,
            "combustibles": [
                {
                    "id": 1,
                    "nombre_corto": "93",
                    "nombre_largo": "Gasolina 93",
                    "suministra": 1,
                    "estacion_id": 42,
                    "precio": "1245.000",
                    "unidad_cobro": "$/L",
                    "actualizado": "hace 2 días",
                    "precio_fecha": "2026-03-23 15:49:50",
                    "updated_at": "2026-03-23 15:49:50",
                    "clase": "Gasolina",
                    "tipo_atencion": 2,
                    "tipo_atencion_nombre": "AutoServicio",
                    "orden": 12
                },
                {
                    "id": 2,
                    "nombre_corto": "97",
                    "nombre_largo": "Gasolina 97",
                    "suministra": 1,
                    "estacion_id": 42,
                    "precio": "1286.000",
                    "unidad_cobro": "$/L",
                    "actualizado": "hace 4 días",
                    "precio_fecha": "2026-03-21 13:08:49",
                    "updated_at": "2026-03-21 13:08:49",
                    "clase": "Gasolina",
                    "tipo_atencion": 2,
                    "tipo_atencion_nombre": "AutoServicio",
                    "orden": 10
                },
                {
                    "id": 3,
                    "nombre_corto": "DI",
                    "nombre_largo": "Petroleo Diesel",
                    "suministra": 1,
                    "estacion_id": 42,
                    "precio": "990.000",
                    "unidad_cobro": "$/L",
                    "actualizado": "hace 2 días",
                    "precio_fecha": "2026-03-23 15:49:50",
                    "updated_at": "2026-03-23 15:49:50",
                    "clase": "Gas",
                    "tipo_atencion": 2,
                    "tipo_atencion_nombre": "AutoServicio",
                    "orden": 9
                },
                {
                    "id": 7,
                    "nombre_corto": "95",
                    "nombre_largo": "Gasolina 95",
                    "suministra": 1,
                    "estacion_id": 42,
                    "precio": "1264.000",
                    "unidad_cobro": "$/L",
                    "actualizado": "hace 2 días",
                    "precio_fecha": "2026-03-23 15:49:50",
                    "updated_at": "2026-03-23 15:49:50",
                    "clase": "Gasolina",
                    "tipo_atencion": 2,
                    "tipo_atencion_nombre": "AutoServicio",
                    "orden": 11
                }
            ],
            "atenciones": [],
            "servicios": [
                {
                    "id": null,
                    "nombre": null,
                    "estacion_id": 42
                },
                {
                    "id": null,
                    "nombre": null,
                    "estacion_id": 42
                },
                {
                    "id": null,
                    "nombre": null,
                    "estacion_id": 42
                }
            ],
            "control_calidad": [],
            "nombre_bencinera": "ARAMCO"
        },
        {
            "id": 44,
            "marca": 151,
            "direccion": "Av. Salvador Allende esq. O'Higgins 0",
            "latitud": "-20.219556311726954",
            "longitud": "-70.13453006744385",
            "region": "Tarapacá",
            "comuna": "Iquique",
            "en_mantenimiento_bandera": 0,
            "electrolinera_bandera": 0,
            "gasolinera_bandera": 1,
            "imagen": "/storage/logo/1715355420_Aramco1.jpg",
            "logo": "https://api.bencinaenlinea.cl/storage/logo/1715355420_Aramco1.jpg",
            "likes": 0,
            "dislikes": 0,
            "usuario_favorito": null,
            "usuario_likes": null,
            "horario": null,
            "combustibles": [
                {
                    "id": 1,
                    "nombre_corto": "93",
                    "nombre_largo": "Gasolina 93",
                    "suministra": 1,
                    "estacion_id": 44,
                    "precio": "1247.000",
                    "unidad_cobro": "$/L",
                    "actualizado": "hace 6 días",
                    "precio_fecha": "2026-03-19 09:21:25",
                    "updated_at": "2026-03-19 09:21:25",
                    "clase": "Gasolina",
                    "tipo_atencion": 2,
                    "tipo_atencion_nombre": "AutoServicio",
                    "orden": 12
                },
                {
                    "id": 2,
                    "nombre_corto": "97",
                    "nombre_largo": "Gasolina 97",
                    "suministra": 1,
                    "estacion_id": 44,
                    "precio": "1296.000",
                    "unidad_cobro": "$/L",
                    "actualizado": "hace 6 días",
                    "precio_fecha": "2026-03-19 09:21:25",
                    "updated_at": "2026-03-19 09:21:25",
                    "clase": "Gasolina",
                    "tipo_atencion": 2,
                    "tipo_atencion_nombre": "AutoServicio",
                    "orden": 10
                },
                {
                    "id": 3,
                    "nombre_corto": "DI",
                    "nombre_largo": "Petroleo Diesel",
                    "suministra": 1,
                    "estacion_id": 44,
                    "precio": "984.000",
                    "unidad_cobro": "$/L",
                    "actualizado": "hace 2 semanas",
                    "precio_fecha": "2026-03-05 12:09:45",
                    "updated_at": "2026-03-05 12:09:45",
                    "clase": "Gas",
                    "tipo_atencion": 2,
                    "tipo_atencion_nombre": "AutoServicio",
                    "orden": 9
                },
                {
                    "id": 7,
                    "nombre_corto": "95",
                    "nombre_largo": "Gasolina 95",
                    "suministra": 1,
                    "estacion_id": 44,
                    "precio": "1268.000",
                    "unidad_cobro": "$/L",
                    "actualizado": "hace 6 días",
                    "precio_fecha": "2026-03-19 09:21:25",
                    "updated_at": "2026-03-19 09:21:25",
                    "clase": "Gasolina",
                    "tipo_atencion": 2,
                    "tipo_atencion_nombre": "AutoServicio",
                    "orden": 11
                }
            ],
            "atenciones": [],
            "servicios": [],
            "control_calidad": [],
            "nombre_bencinera": "ARAMCO"
        },
        {
            "id": 45,
            "marca": 151,
            "direccion": "Pedro Prado esq. Gómez Carreño 0",
            "latitud": "-20.233006140888285",
            "longitud": "-70.1355493068695",
            "region": "Tarapacá",
            "comuna": "Iquique",
            "en_mantenimiento_bandera": 0,
            "electrolinera_bandera": 0,
            "gasolinera_bandera": 1,
            "imagen": "/storage/logo/1715355420_Aramco1.jpg",
            "logo": "https://api.bencinaenlinea.cl/storage/logo/1715355420_Aramco1.jpg",
            "likes": 0,
            "dislikes": 0,
            "usuario_favorito": null,
            "usuario_likes": null,
            "horario": null,
            "combustibles": [
                {
                    "id": 1,
                    "nombre_corto": "93",
                    "nombre_largo": "Gasolina 93",
                    "suministra": 1,
                    "estacion_id": 45,
                    "precio": "1251.000",
                    "unidad_cobro": "$/L",
                    "actualizado": "hace 6 días",
                    "precio_fecha": "2026-03-19 09:24:03",
                    "updated_at": "2026-03-19 09:24:03",
                    "clase": "Gasolina",
                    "tipo_atencion": 2,
                    "tipo_atencion_nombre": "AutoServicio",
                    "orden": 12
                },
                {
                    "id": 2,
                    "nombre_corto": "97",
                    "nombre_largo": "Gasolina 97",
                    "suministra": 1,
                    "estacion_id": 45,
                    "precio": "1291.000",
                    "unidad_cobro": "$/L",
                    "actualizado": "hace 6 días",
                    "precio_fecha": "2026-03-19 09:24:03",
                    "updated_at": "2026-03-19 09:24:03",
                    "clase": "Gasolina",
                    "tipo_atencion": 2,
                    "tipo_atencion_nombre": "AutoServicio",
                    "orden": 10
                },
                {
                    "id": 3,
                    "nombre_corto": "DI",
                    "nombre_largo": "Petroleo Diesel",
                    "suministra": 1,
                    "estacion_id": 45,
                    "precio": "983.000",
                    "unidad_cobro": "$/L",
                    "actualizado": "hace 6 días",
                    "precio_fecha": "2026-03-19 09:24:03",
                    "updated_at": "2026-03-19 09:24:03",
                    "clase": "Gas",
                    "tipo_atencion": 2,
                    "tipo_atencion_nombre": "AutoServicio",
                    "orden": 9
                },
                {
                    "id": 7,
                    "nombre_corto": "95",
                    "nombre_largo": "Gasolina 95",
                    "suministra": 1,
                    "estacion_id": 45,
                    "precio": "1270.000",
                    "unidad_cobro": "$/L",
                    "actualizado": "hace 6 días",
                    "precio_fecha": "2026-03-19 09:24:03",
                    "updated_at": "2026-03-19 09:24:03",
                    "clase": "Gasolina",
                    "tipo_atencion": 2,
                    "tipo_atencion_nombre": "AutoServicio",
                    "orden": 11
                }
            ],
            "atenciones": [],
            "servicios": [],
            "control_calidad": [],
            "nombre_bencinera": "ARAMCO"
        },
        {
            "id": 47,
            "marca": 4,
            "direccion": "OHiggins 2280",
            "latitud": "-20.219516041030868",
            "longitud": "-70.13424038887024",
            "region": "Tarapacá",
            "comuna": "Iquique",
            "en_mantenimiento_bandera": 0,
            "electrolinera_bandera": 0,
            "gasolinera_bandera": 1,
            "imagen": "/storage/logo/1697479767_Shell.png",
            "logo": "https://api.bencinaenlinea.cl/storage/logo/1697479767_Shell.png",
            "likes": 0,
            "dislikes": 0,
            "usuario_favorito": null,
            "usuario_likes": null,
            "horario": null,
            "combustibles": [
                {
                    "id": 1,
                    "nombre_corto": "93",
                    "nombre_largo": "Gasolina 93",
                    "suministra": 1,
                    "estacion_id": 47,
                    "precio": "1247.000",
                    "unidad_cobro": "$/L",
                    "actualizado": "hace 6 días",
                    "precio_fecha": "2026-03-19 16:05:56",
                    "updated_at": "2026-03-19 16:05:56",
                    "clase": "Gasolina",
                    "tipo_atencion": 2,
                    "tipo_atencion_nombre": "AutoServicio",
                    "orden": 12
                },
                {
                    "id": 2,
                    "nombre_corto": "97",
                    "nombre_largo": "Gasolina 97",
                    "suministra": 1,
                    "estacion_id": 47,
                    "precio": "1297.000",
                    "unidad_cobro": "$/L",
                    "actualizado": "hace 6 días",
                    "precio_fecha": "2026-03-19 16:05:56",
                    "updated_at": "2026-03-19 16:05:56",
                    "clase": "Gasolina",
                    "tipo_atencion": 2,
                    "tipo_atencion_nombre": "AutoServicio",
                    "orden": 10
                },
                {
                    "id": 3,
                    "nombre_corto": "DI",
                    "nombre_largo": "Petroleo Diesel",
                    "suministra": 1,
                    "estacion_id": 47,
                    "precio": "984.000",
                    "unidad_cobro": "$/L",
                    "actualizado": "hace 1 semana",
                    "precio_fecha": "2026-03-12 10:11:02",
                    "updated_at": "2026-03-12 10:11:02",
                    "clase": "Gas",
                    "tipo_atencion": 2,
                    "tipo_atencion_nombre": "AutoServicio",
                    "orden": 9
                },
                {
                    "id": 7,
                    "nombre_corto": "95",
                    "nombre_largo": "Gasolina 95",
                    "suministra": 1,
                    "estacion_id": 47,
                    "precio": "1268.000",
                    "unidad_cobro": "$/L",
                    "actualizado": "hace 6 días",
                    "precio_fecha": "2026-03-19 16:05:56",
                    "updated_at": "2026-03-19 16:05:56",
                    "clase": "Gasolina",
                    "tipo_atencion": 2,
                    "tipo_atencion_nombre": "AutoServicio",
                    "orden": 11
                }
            ],
            "atenciones": [],
            "servicios": [
                {
                    "id": null,
                    "nombre": null,
                    "estacion_id": 47
                },
                {
                    "id": null,
                    "nombre": null,
                    "estacion_id": 47
                },
                {
                    "id": null,
                    "nombre": null,
                    "estacion_id": 47
                }
            ],
            "control_calidad": [],
            "nombre_bencinera": "SHELL"
        },
        {
            "id": 48,
            "marca": 4,
            "direccion": "Avda. Arturo Prat 1850",
            "latitud": "-20.24222202487748",
            "longitud": "-70.14248013496399",
            "region": "Tarapacá",
            "comuna": "Iquique",
            "en_mantenimiento_bandera": 0,
            "electrolinera_bandera": 0,
            "gasolinera_bandera": 1,
            "imagen": "/storage/logo/1697479767_Shell.png",
            "logo": "https://api.bencinaenlinea.cl/storage/logo/1697479767_Shell.png",
            "likes": 0,
            "dislikes": 0,
            "usuario_favorito": null,
            "usuario_likes": null,
            "horario": null,
            "combustibles": [
                {
                    "id": 1,
                    "nombre_corto": "93",
                    "nombre_largo": "Gasolina 93",
                    "suministra": 1,
                    "estacion_id": 48,
                    "precio": "1245.000",
                    "unidad_cobro": "$/L",
                    "actualizado": "hace 5 días",
                    "precio_fecha": "2026-03-20 18:35:48",
                    "updated_at": "2026-03-20 18:35:48",
                    "clase": "Gasolina",
                    "tipo_atencion": 2,
                    "tipo_atencion_nombre": "AutoServicio",
                    "orden": 12
                },
                {
                    "id": 2,
                    "nombre_corto": "97",
                    "nombre_largo": "Gasolina 97",
                    "suministra": 1,
                    "estacion_id": 48,
                    "precio": "1291.000",
                    "unidad_cobro": "$/L",
                    "actualizado": "hace 5 días",
                    "precio_fecha": "2026-03-20 18:35:48",
                    "updated_at": "2026-03-20 18:35:48",
                    "clase": "Gasolina",
                    "tipo_atencion": 2,
                    "tipo_atencion_nombre": "AutoServicio",
                    "orden": 10
                },
                {
                    "id": 3,
                    "nombre_corto": "DI",
                    "nombre_largo": "Petroleo Diesel",
                    "suministra": 1,
                    "estacion_id": 48,
                    "precio": "990.000",
                    "unidad_cobro": "$/L",
                    "actualizado": "hace 5 días",
                    "precio_fecha": "2026-03-20 18:35:48",
                    "updated_at": "2026-03-20 18:35:48",
                    "clase": "Gas",
                    "tipo_atencion": 2,
                    "tipo_atencion_nombre": "AutoServicio",
                    "orden": 9
                },
                {
                    "id": 7,
                    "nombre_corto": "95",
                    "nombre_largo": "Gasolina 95",
                    "suministra": 1,
                    "estacion_id": 48,
                    "precio": "1264.000",
                    "unidad_cobro": "$/L",
                    "actualizado": "hace 5 días",
                    "precio_fecha": "2026-03-20 18:35:48",
                    "updated_at": "2026-03-20 18:35:48",
                    "clase": "Gasolina",
                    "tipo_atencion": 2,
                    "tipo_atencion_nombre": "AutoServicio",
                    "orden": 11
                },
                {
                    "id": 8,
                    "nombre_corto": "A93",
                    "nombre_largo": "Gasolina 93",
                    "suministra": 1,
                    "estacion_id": 48,
                    "precio": "1230.000",
                    "unidad_cobro": "$/L",
                    "actualizado": "hace 5 días",
                    "precio_fecha": "2026-03-20 18:35:48",
                    "updated_at": "2026-03-20 18:35:48",
                    "clase": "Gas",
                    "tipo_atencion": 1,
                    "tipo_atencion_nombre": "Asistido",
                    "orden": 5
                },
                {
                    "id": 9,
                    "nombre_corto": "A95",
                    "nombre_largo": "Gasolina 95",
                    "suministra": 1,
                    "estacion_id": 48,
                    "precio": "1249.000",
                    "unidad_cobro": "$/L",
                    "actualizado": "hace 5 días",
                    "precio_fecha": "2026-03-20 18:35:48",
                    "updated_at": "2026-03-20 18:35:48",
                    "clase": "Gas",
                    "tipo_atencion": 1,
                    "tipo_atencion_nombre": "Asistido",
                    "orden": 4
                },
                {
                    "id": 10,
                    "nombre_corto": "A97",
                    "nombre_largo": "Gasolina 97",
                    "suministra": 1,
                    "estacion_id": 48,
                    "precio": "1276.000",
                    "unidad_cobro": "$/L",
                    "actualizado": "hace 5 días",
                    "precio_fecha": "2026-03-20 18:35:48",
                    "updated_at": "2026-03-20 18:35:48",
                    "clase": "Gas",
                    "tipo_atencion": 1,
                    "tipo_atencion_nombre": "Asistido",
                    "orden": 3
                },
                {
                    "id": 11,
                    "nombre_corto": "ADI",
                    "nombre_largo": "Petroleo Diesel",
                    "suministra": 1,
                    "estacion_id": 48,
                    "precio": "975.000",
                    "unidad_cobro": "$/L",
                    "actualizado": "hace 5 días",
                    "precio_fecha": "2026-03-20 18:35:48",
                    "updated_at": "2026-03-20 18:35:48",
                    "clase": "Gas",
                    "tipo_atencion": 1,
                    "tipo_atencion_nombre": "Asistido",
                    "orden": 2
                }
            ],
            "atenciones": [],
            "servicios": [
                {
                    "id": null,
                    "nombre": null,
                    "estacion_id": 48
                },
                {
                    "id": null,
                    "nombre": null,
                    "estacion_id": 48
                },
                {
                    "id": null,
                    "nombre": null,
                    "estacion_id": 48
                },
                {
                    "id": null,
                    "nombre": null,
                    "estacion_id": 48
                },
                {
                    "id": null,
                    "nombre": null,
                    "estacion_id": 48
                },
                {
                    "id": null,
                    "nombre": null,
                    "estacion_id": 48
                }
            ],
            "control_calidad": [],
            "nombre_bencinera": "SHELL"
        },
        {
            "id": 49,
            "marca": 4,
            "direccion": "Cespedes Gonzalez 1685",
            "latitud": "-20.224856851100128",
            "longitud": "-70.1400500535965",
            "region": "Tarapacá",
            "comuna": "Iquique",
            "en_mantenimiento_bandera": 0,
            "electrolinera_bandera": 0,
            "gasolinera_bandera": 1,
            "imagen": "/storage/logo/1697479767_Shell.png",
            "logo": "https://api.bencinaenlinea.cl/storage/logo/1697479767_Shell.png",
            "likes": 0,
            "dislikes": 0,
            "usuario_favorito": null,
            "usuario_likes": null,
            "horario": null,
            "combustibles": [
                {
                    "id": 1,
                    "nombre_corto": "93",
                    "nombre_largo": "Gasolina 93",
                    "suministra": 1,
                    "estacion_id": 49,
                    "precio": "1245.000",
                    "unidad_cobro": "$/L",
                    "actualizado": "hace 6 días",
                    "precio_fecha": "2026-03-19 12:50:50",
                    "updated_at": "2026-03-19 12:50:50",
                    "clase": "Gasolina",
                    "tipo_atencion": 2,
                    "tipo_atencion_nombre": "AutoServicio",
                    "orden": 12
                },
                {
                    "id": 2,
                    "nombre_corto": "97",
                    "nombre_largo": "Gasolina 97",
                    "suministra": 1,
                    "estacion_id": 49,
                    "precio": "1289.000",
                    "unidad_cobro": "$/L",
                    "actualizado": "hace 6 días",
                    "precio_fecha": "2026-03-19 12:50:51",
                    "updated_at": "2026-03-19 12:50:51",
                    "clase": "Gasolina",
                    "tipo_atencion": 2,
                    "tipo_atencion_nombre": "AutoServicio",
                    "orden": 10
                },
                {
                    "id": 3,
                    "nombre_corto": "DI",
                    "nombre_largo": "Petroleo Diesel",
                    "suministra": 1,
                    "estacion_id": 49,
                    "precio": "990.000",
                    "unidad_cobro": "$/L",
                    "actualizado": "hace 6 días",
                    "precio_fecha": "2026-03-19 12:50:51",
                    "updated_at": "2026-03-19 12:50:51",
                    "clase": "Gas",
                    "tipo_atencion": 2,
                    "tipo_atencion_nombre": "AutoServicio",
                    "orden": 9
                },
                {
                    "id": 7,
                    "nombre_corto": "95",
                    "nombre_largo": "Gasolina 95",
                    "suministra": 1,
                    "estacion_id": 49,
                    "precio": "1264.000",
                    "unidad_cobro": "$/L",
                    "actualizado": "hace 6 días",
                    "precio_fecha": "2026-03-19 12:50:51",
                    "updated_at": "2026-03-19 12:50:51",
                    "clase": "Gasolina",
                    "tipo_atencion": 2,
                    "tipo_atencion_nombre": "AutoServicio",
                    "orden": 11
                }
            ],
            "atenciones": [],
            "servicios": [
                {
                    "id": null,
                    "nombre": null,
                    "estacion_id": 49
                },
                {
                    "id": null,
                    "nombre": null,
                    "estacion_id": 49
                },
                {
                    "id": null,
                    "nombre": null,
                    "estacion_id": 49
                },
                {
                    "id": null,
                    "nombre": null,
                    "estacion_id": 49
                }
            ],
            "control_calidad": [],
            "nombre_bencinera": "SHELL"
        },
        {
            "id": 50,
            "marca": 4,
            "direccion": "Genaro Gallo 2361",
            "latitud": "-20.23158419860352",
            "longitud": "-70.13776749372482",
            "region": "Tarapacá",
            "comuna": "Iquique",
            "en_mantenimiento_bandera": 0,
            "electrolinera_bandera": 0,
            "gasolinera_bandera": 1,
            "imagen": "/storage/logo/1697479767_Shell.png",
            "logo": "https://api.bencinaenlinea.cl/storage/logo/1697479767_Shell.png",
            "likes": 0,
            "dislikes": 0,
            "usuario_favorito": null,
            "usuario_likes": null,
            "horario": null,
            "combustibles": [
                {
                    "id": 1,
                    "nombre_corto": "93",
                    "nombre_largo": "Gasolina 93",
                    "suministra": 1,
                    "estacion_id": 50,
                    "precio": "1241.000",
                    "unidad_cobro": "$/L",
                    "actualizado": "hace 6 días",
                    "precio_fecha": "2026-03-19 10:06:03",
                    "updated_at": "2026-03-19 10:06:03",
                    "clase": "Gasolina",
                    "tipo_atencion": 2,
                    "tipo_atencion_nombre": "AutoServicio",
                    "orden": 12
                },
                {
                    "id": 2,
                    "nombre_corto": "97",
                    "nombre_largo": "Gasolina 97",
                    "suministra": 1,
                    "estacion_id": 50,
                    "precio": "1288.000",
                    "unidad_cobro": "$/L",
                    "actualizado": "hace 6 días",
                    "precio_fecha": "2026-03-19 10:06:03",
                    "updated_at": "2026-03-19 10:06:03",
                    "clase": "Gasolina",
                    "tipo_atencion": 2,
                    "tipo_atencion_nombre": "AutoServicio",
                    "orden": 10
                },
                {
                    "id": 3,
                    "nombre_corto": "DI",
                    "nombre_largo": "Petroleo Diesel",
                    "suministra": 1,
                    "estacion_id": 50,
                    "precio": "974.000",
                    "unidad_cobro": "$/L",
                    "actualizado": "hace 6 horas",
                    "precio_fecha": "2026-03-25 15:20:51",
                    "updated_at": "2026-03-25 15:20:51",
                    "clase": "Gas",
                    "tipo_atencion": 2,
                    "tipo_atencion_nombre": "AutoServicio",
                    "orden": 9
                },
                {
                    "id": 7,
                    "nombre_corto": "95",
                    "nombre_largo": "Gasolina 95",
                    "suministra": 1,
                    "estacion_id": 50,
                    "precio": "1260.000",
                    "unidad_cobro": "$/L",
                    "actualizado": "hace 6 días",
                    "precio_fecha": "2026-03-19 10:06:03",
                    "updated_at": "2026-03-19 10:06:03",
                    "clase": "Gasolina",
                    "tipo_atencion": 2,
                    "tipo_atencion_nombre": "AutoServicio",
                    "orden": 11
                }
            ],
            "atenciones": [],
            "servicios": [],
            "control_calidad": [],
            "nombre_bencinera": "SHELL"
        },
        {
            "id": 51,
            "marca": 4,
            "direccion": "Manuel Rodríguez/Vivar 705",
            "latitud": "-20.223565710714904",
            "longitud": "-70.14910250902176",
            "region": "Tarapacá",
            "comuna": "Iquique",
            "en_mantenimiento_bandera": 0,
            "electrolinera_bandera": 0,
            "gasolinera_bandera": 1,
            "imagen": "/storage/logo/1697479767_Shell.png",
            "logo": "https://api.bencinaenlinea.cl/storage/logo/1697479767_Shell.png",
            "likes": 0,
            "dislikes": 0,
            "usuario_favorito": null,
            "usuario_likes": null,
            "horario": null,
            "combustibles": [
                {
                    "id": 1,
                    "nombre_corto": "93",
                    "nombre_largo": "Gasolina 93",
                    "suministra": 1,
                    "estacion_id": 51,
                    "precio": "1245.000",
                    "unidad_cobro": "$/L",
                    "actualizado": "hace 5 días",
                    "precio_fecha": "2026-03-20 18:35:44",
                    "updated_at": "2026-03-20 18:35:44",
                    "clase": "Gasolina",
                    "tipo_atencion": 2,
                    "tipo_atencion_nombre": "AutoServicio",
                    "orden": 12
                },
                {
                    "id": 2,
                    "nombre_corto": "97",
                    "nombre_largo": "Gasolina 97",
                    "suministra": 1,
                    "estacion_id": 51,
                    "precio": "1292.000",
                    "unidad_cobro": "$/L",
                    "actualizado": "hace 5 días",
                    "precio_fecha": "2026-03-20 18:35:44",
                    "updated_at": "2026-03-20 18:35:44",
                    "clase": "Gasolina",
                    "tipo_atencion": 2,
                    "tipo_atencion_nombre": "AutoServicio",
                    "orden": 10
                },
                {
                    "id": 3,
                    "nombre_corto": "DI",
                    "nombre_largo": "Petroleo Diesel",
                    "suministra": 1,
                    "estacion_id": 51,
                    "precio": "990.000",
                    "unidad_cobro": "$/L",
                    "actualizado": "hace 5 días",
                    "precio_fecha": "2026-03-20 18:35:44",
                    "updated_at": "2026-03-20 18:35:44",
                    "clase": "Gas",
                    "tipo_atencion": 2,
                    "tipo_atencion_nombre": "AutoServicio",
                    "orden": 9
                },
                {
                    "id": 7,
                    "nombre_corto": "95",
                    "nombre_largo": "Gasolina 95",
                    "suministra": 1,
                    "estacion_id": 51,
                    "precio": "1264.000",
                    "unidad_cobro": "$/L",
                    "actualizado": "hace 5 días",
                    "precio_fecha": "2026-03-20 18:35:44",
                    "updated_at": "2026-03-20 18:35:44",
                    "clase": "Gasolina",
                    "tipo_atencion": 2,
                    "tipo_atencion_nombre": "AutoServicio",
                    "orden": 11
                },
                {
                    "id": 8,
                    "nombre_corto": "A93",
                    "nombre_largo": "Gasolina 93",
                    "suministra": 1,
                    "estacion_id": 51,
                    "precio": "1237.000",
                    "unidad_cobro": "$/L",
                    "actualizado": "hace 5 días",
                    "precio_fecha": "2026-03-20 18:35:44",
                    "updated_at": "2026-03-20 18:35:44",
                    "clase": "Gas",
                    "tipo_atencion": 1,
                    "tipo_atencion_nombre": "Asistido",
                    "orden": 5
                },
                {
                    "id": 9,
                    "nombre_corto": "A95",
                    "nombre_largo": "Gasolina 95",
                    "suministra": 1,
                    "estacion_id": 51,
                    "precio": "1256.000",
                    "unidad_cobro": "$/L",
                    "actualizado": "hace 5 días",
                    "precio_fecha": "2026-03-20 18:35:44",
                    "updated_at": "2026-03-20 18:35:44",
                    "clase": "Gas",
                    "tipo_atencion": 1,
                    "tipo_atencion_nombre": "Asistido",
                    "orden": 4
                },
                {
                    "id": 10,
                    "nombre_corto": "A97",
                    "nombre_largo": "Gasolina 97",
                    "suministra": 1,
                    "estacion_id": 51,
                    "precio": "1284.000",
                    "unidad_cobro": "$/L",
                    "actualizado": "hace 5 días",
                    "precio_fecha": "2026-03-20 18:35:44",
                    "updated_at": "2026-03-20 18:35:44",
                    "clase": "Gas",
                    "tipo_atencion": 1,
                    "tipo_atencion_nombre": "Asistido",
                    "orden": 3
                },
                {
                    "id": 11,
                    "nombre_corto": "ADI",
                    "nombre_largo": "Petroleo Diesel",
                    "suministra": 1,
                    "estacion_id": 51,
                    "precio": "982.000",
                    "unidad_cobro": "$/L",
                    "actualizado": "hace 5 días",
                    "precio_fecha": "2026-03-20 18:35:44",
                    "updated_at": "2026-03-20 18:35:44",
                    "clase": "Gas",
                    "tipo_atencion": 1,
                    "tipo_atencion_nombre": "Asistido",
                    "orden": 2
                }
            ],
            "atenciones": [],
            "servicios": [
                {
                    "id": null,
                    "nombre": null,
                    "estacion_id": 51
                },
                {
                    "id": null,
                    "nombre": null,
                    "estacion_id": 51
                },
                {
                    "id": null,
                    "nombre": null,
                    "estacion_id": 51
                },
                {
                    "id": null,
                    "nombre": null,
                    "estacion_id": 51
                }
            ],
            "control_calidad": [],
            "nombre_bencinera": "SHELL"
        }
    ]
}